breeze_langdetect-0.2.0.dist-info/METADATA
breeze_langdetect-0.2.0.dist-info/WHEEL
breeze_langdetect-0.2.0.dist-info/licenses/LICENSE
breeze_langdetect/__init__.py
breeze_langdetect/breeze_langdetect.cp312-win32.pyd
breeze_langdetect-0.2.0.dist-info/RECORD
