Metadata-Version: 2.4
Name: breeze-langdetect
Version: 0.2.0
Classifier: Programming Language :: Rust
Classifier: Programming Language :: Python :: Implementation :: CPython
Classifier: Programming Language :: Python :: Implementation :: PyPy
Requires-Dist: pytest>=7.0 ; extra == 'dev'
Requires-Dist: maturin>=1.8.6 ; extra == 'dev'
Provides-Extra: dev
License-File: LICENSE
Requires-Python: >=3.8
